<PlayBook>
	<BayesPlays>
		<R4_A1-1S_2D/>
		<R4_S1-1A_2D/>
		<R5_A1-1S_1D_1AS_1SP/>
		<R5_A1-1S_2D_1AS/>
		<R5_A2-1P1S_2D/>
		<R5_A3-2P1S_1D/>
		<R5_D1_1A_1CM_1FD/>
		<R5_D2_1A_1AS/>
		<R5_D2_2CM/>
		<R5_S2-1A_1AS_2D/>
	</BayesPlays>
	<RefereePlays>
		<Ref4_Cornerkick/>
		<Ref4_Indirect/>
		<Ref4_Kickoff/>
		<Ref4_Kickoff_Def/>
		<Ref4_IndirectV2/>
		<Ref_Cornerkick/>
		<Ref_Cornerkick_Def_l/>
		<Ref_Cornerkick_Def_r/>
		<Ref_Halt/>
		<Ref_Indirect/>
		<Ref_Indirect_Def/>
		<Ref_Kickoff/>
		<Ref_Kickoff_Def/>
		<Ref_Penalty_Def/>
		<Ref_Stop/>
		<Ref_Penalty_kick/>
		<Ref_Kickoff_simple/>
		<R5_CM5/>
		<Ref_Cornerkick_Def_l_CM/>
		<Ref_Cornerkick_Def_r_CM/>
		<Ref_Indirect_Def_CM/>
		<Ref_Indirect_1p1s/>
		<Ref_Immortalkick/>
	</RefereePlays>
	<TestPlays>
		<chipkick_test/>
		<d_challege/>
		<ChipAndShoot/>
	</TestPlays>
</PlayBook>
